{
	"configurations" : 
	[
		{
			"directories" : 
			[
				{
					"build" : ".",
					"jsonFile" : "directory-.-Debug-d0094a50bb2071803777.json",
					"minimumCMakeVersion" : 
					{
						"string" : "3.23"
					},
					"projectIndex" : 0,
					"source" : ".",
					"targetIndexes" : 
					[
						0
					]
				}
			],
			"name" : "Debug",
			"projects" : 
			[
				{
					"directoryIndexes" : 
					[
						0
					],
					"name" : "magic",
					"targetIndexes" : 
					[
						0
					]
				}
			],
			"targets" : 
			[
				{
					"directoryIndex" : 0,
					"id" : "magic::@6890427a1f51a3e7e1df",
					"jsonFile" : "target-magic-Debug-63dc9eb2e4c6c4d690be.json",
					"name" : "magic",
					"projectIndex" : 0
				}
			]
		}
	],
	"kind" : "codemodel",
	"paths" : 
	{
		"build" : "D:/CLCK/Desktop/C++/11.21/magic/cmake-build-debug",
		"source" : "D:/CLCK/Desktop/C++/11.21/magic"
	},
	"version" : 
	{
		"major" : 2,
		"minor" : 4
	}
}
